{
  "schema": "fullbleed.template_flagging_smoke.v1",
  "ok": true,
  "validation_mode": "fullbleed_bindings_and_compose_contract",
  "template_pdf": "C:\\dev\\workbench\\fullbleed-official\\examples\\template-flagging-smoke\\output\\rgb_template_3pages.pdf",
  "sequence": [
    "blue",
    "red",
    "green",
    "blue",
    "green",
    "red",
    "blue",
    "red",
    "green",
    "blue"
  ],
  "raw": {
    "overlay_pdf": "C:\\dev\\workbench\\fullbleed-official\\examples\\template-flagging-smoke\\output\\overlay_raw.pdf",
    "composed_pdf": "C:\\dev\\workbench\\fullbleed-official\\examples\\template-flagging-smoke\\output\\composed_raw.pdf",
    "compose": {
      "ok": true,
      "pages_written": 10
    },
    "validation": {
      "ok": true,
      "page_count": 10,
      "binding_checks": [
        {
          "page": 1,
          "expected_template_id": "tpl-blue",
          "bound_template_id": "tpl-blue",
          "binding_ok": true
        },
        {
          "page": 2,
          "expected_template_id": "tpl-red",
          "bound_template_id": "tpl-red",
          "binding_ok": true
        },
        {
          "page": 3,
          "expected_template_id": "tpl-green",
          "bound_template_id": "tpl-green",
          "binding_ok": true
        },
        {
          "page": 4,
          "expected_template_id": "tpl-blue",
          "bound_template_id": "tpl-blue",
          "binding_ok": true
        },
        {
          "page": 5,
          "expected_template_id": "tpl-green",
          "bound_template_id": "tpl-green",
          "binding_ok": true
        },
        {
          "page": 6,
          "expected_template_id": "tpl-red",
          "bound_template_id": "tpl-red",
          "binding_ok": true
        },
        {
          "page": 7,
          "expected_template_id": "tpl-blue",
          "bound_template_id": "tpl-blue",
          "binding_ok": true
        },
        {
          "page": 8,
          "expected_template_id": "tpl-red",
          "bound_template_id": "tpl-red",
          "binding_ok": true
        },
        {
          "page": 9,
          "expected_template_id": "tpl-green",
          "bound_template_id": "tpl-green",
          "binding_ok": true
        },
        {
          "page": 10,
          "expected_template_id": "tpl-blue",
          "bound_template_id": "tpl-blue",
          "binding_ok": true
        }
      ]
    }
  },
  "el": {
    "overlay_pdf": "C:\\dev\\workbench\\fullbleed-official\\examples\\template-flagging-smoke\\output\\overlay_el.pdf",
    "composed_pdf": "C:\\dev\\workbench\\fullbleed-official\\examples\\template-flagging-smoke\\output\\composed_el.pdf",
    "compose": {
      "ok": true,
      "pages_written": 10
    },
    "validation": {
      "ok": true,
      "page_count": 10,
      "binding_checks": [
        {
          "page": 1,
          "expected_template_id": "tpl-blue",
          "bound_template_id": "tpl-blue",
          "binding_ok": true
        },
        {
          "page": 2,
          "expected_template_id": "tpl-red",
          "bound_template_id": "tpl-red",
          "binding_ok": true
        },
        {
          "page": 3,
          "expected_template_id": "tpl-green",
          "bound_template_id": "tpl-green",
          "binding_ok": true
        },
        {
          "page": 4,
          "expected_template_id": "tpl-blue",
          "bound_template_id": "tpl-blue",
          "binding_ok": true
        },
        {
          "page": 5,
          "expected_template_id": "tpl-green",
          "bound_template_id": "tpl-green",
          "binding_ok": true
        },
        {
          "page": 6,
          "expected_template_id": "tpl-red",
          "bound_template_id": "tpl-red",
          "binding_ok": true
        },
        {
          "page": 7,
          "expected_template_id": "tpl-blue",
          "bound_template_id": "tpl-blue",
          "binding_ok": true
        },
        {
          "page": 8,
          "expected_template_id": "tpl-red",
          "bound_template_id": "tpl-red",
          "binding_ok": true
        },
        {
          "page": 9,
          "expected_template_id": "tpl-green",
          "bound_template_id": "tpl-green",
          "binding_ok": true
        },
        {
          "page": 10,
          "expected_template_id": "tpl-blue",
          "bound_template_id": "tpl-blue",
          "binding_ok": true
        }
      ]
    }
  }
}